README
setup.py
bin/txtbudget
txtbudget/__init__.py
txtbudget/commands.py
txtbudget/config.py
txtbudget/queries.py
txtbudget/simplecmd.py
txtbudget/tests.py
txtbudget/utils.py
txtbudget.egg-info/PKG-INFO
txtbudget.egg-info/SOURCES.txt
txtbudget.egg-info/dependency_links.txt
txtbudget.egg-info/requires.txt
txtbudget.egg-info/top_level.txt