Metadata-Version: 1.0
Name: txtbudget
Version: 1.0.4
Summary: Text based budget scheduler
Home-page: UNKNOWN
Author: Eric Moritz
Author-email: eric@themoritzfamily.com
License: UNKNOWN
Platform: UNKNOWN
